jmlopez_m-0.37.0.data/scripts/endRelease
jmlopez_m-0.37.0.data/scripts/m
jmlopez_m-0.37.0.data/scripts/reviewRelease
jmlopez_m-0.37.0.data/scripts/startHotfix
jmlopez_m-0.37.0.data/scripts/startRelease
m/__init__.py
m/__main__.py
m/git.py
m/py.typed
m/pydantic.py
m/version.py
m/ci/__init__.py
m/ci/assert_branch.py
m/ci/config.py
m/ci/end_release.py
m/ci/git_env.py
m/ci/init.py
m/ci/m_blueprints.py
m/ci/m_env.py
m/ci/release_env.py
m/ci/release_setup.py
m/ci/release_utils.py
m/ci/review_release.py
m/ci/start_release.py
m/ci/types.py
m/ci/versioning.py
m/ci/celt/__init__.py
m/ci/celt/post_processor.py
m/ci/celt/core/__init__.py
m/ci/celt/core/io.py
m/ci/celt/core/process.py
m/ci/celt/core/types.py
m/ci/celt/post_processors/__init__.py
m/ci/celt/post_processors/eslint.py
m/ci/celt/post_processors/pycodestyle.py
m/ci/celt/post_processors/pylint.py
m/ci/celt/post_processors/ruff.py
m/ci/celt/post_processors/typescript.py
m/ci/docker/__init__.py
m/ci/docker/config.py
m/ci/docker/docker_build.py
m/ci/docker/env.py
m/ci/docker/filenames.py
m/ci/docker/gh_workflow_multi.py
m/ci/docker/gh_workflow_single.py
m/ci/docker/image.py
m/ci/docker/shell_command.py
m/ci/docker/shell_scripts.py
m/ci/docker/tags.py
m/ci/docker/workflow_input.py
m/cli/__init__.py
m/cli/args.py
m/cli/cli.py
m/cli/handlers.py
m/cli/validators.py
m/cli/commands/__init__.py
m/cli/commands/blueprints.py
m/cli/commands/end_release.py
m/cli/commands/init.py
m/cli/commands/json.py
m/cli/commands/jsonq.py
m/cli/commands/review_release.py
m/cli/commands/start_hotfix.py
m/cli/commands/start_release.py
m/cli/commands/ci/__init__.py
m/cli/commands/ci/assert_branch.py
m/cli/commands/ci/bump_version.py
m/cli/commands/ci/celt.py
m/cli/commands/ci/env.py
m/cli/commands/ci/npm_tag.py
m/cli/commands/ci/release_setup.py
m/cli/commands/devcontainer/__init__.py
m/cli/commands/devcontainer/bashrc.py
m/cli/commands/devcontainer/greet.py
m/cli/commands/devcontainer/pnpm.py
m/cli/commands/devcontainer/pnpm_setup.py
jmlopez_m-0.37.0.dist-info/LICENSE
jmlopez_m-0.37.0.dist-info/METADATA
jmlopez_m-0.37.0.dist-info/WHEEL
jmlopez_m-0.37.0.dist-info/top_level.txt
jmlopez_m-0.37.0.dist-info/RECORD
