Metadata-Version: 2.2
Name: jmlopez-m
Version: 0.37.0
Summary: m
Home-page: https://github.com/jmlopez-rod/m
Author: Manuel Lopez
Author-email: jmlopez.rod@gmail.com
Project-URL: Bug Tracker, https://github.com/jmlopez-rod/m/issues
Classifier: Programming Language :: Python :: 3
Classifier: License :: OSI Approved :: MIT License
Classifier: Operating System :: OS Independent
Requires-Python: >=3.10
License-File: LICENSE
Requires-Dist: typing_extensions
Requires-Dist: pydantic>=2.1.0
Requires-Dist: pyyaml
Requires-Dist: packaging
Requires-Dist: pygments>=2.14.0
Requires-Dist: argcomplete
Dynamic: author
Dynamic: author-email
Dynamic: classifier
Dynamic: description
Dynamic: description-content-type
Dynamic: home-page
Dynamic: project-url
Dynamic: requires-dist
Dynamic: requires-python
Dynamic: summary
